{
  "name": "inspinia-asset",
  "description": "Assets for inspinia admin panel.",
  "main": "",
  "dependencies": {
    "font-awesome": "~4.0"
  },
  "license": "MIT",
  "ignore": [],
  "homepage": "https://github.com/ImAnilChaudhari/inspinia-asset",
  "_release": "987fd471f8",
  "_resolution": {
    "type": "branch",
    "branch": "master",
    "commit": "987fd471f839160959a6609d985bee6ef74b285d"
  },
  "_source": "https://github.com/ImAnilChaudhari/inspinia-asset.git",
  "_target": "*",
  "_originalSource": "https://github.com/ImAnilChaudhari/inspinia-asset.git"
}